Verilog code of processor/MIPS.v
module MIPS(
    input clk1,
    input clk2
);
parameter 
ADD = 6'b000000,
SUB = 6'b000001,
AND = 6'b000010,
OR = 6'b000011,
SLT = 6'b000100,
MUL = 6'b000101,
HLT = 6'b111111,

LW = 6'b001000,
SW = 6'b001001,
ADDI = 6'b001010,
SUBI = 6'b001011,
SLTI = 6'b001100,
BNEQZ = 6'b001101,
BEQZ = 6'b001110;

parameter
    RR_ALU = 3'B000,
    RM_ALU = 3'B001,
    LOAD = 3'B010,
    STORE = 3'B011,
    BRANCH = 3'B100,
    HALT = 3'B101;

reg TAKEN_BRANCH, HALTED;

reg [31:0] reg_bank [0:31];
reg [31:0] mem [0:1023];

reg EX_MEM_COND;
reg [2:0] ID_EX_TYPE, EX_MEM_TYPE, MEM_WB_TYPE;
reg [31:0] PC, IF_ID_NPC, IF_ID_IR;
reg [31:0] ID_EX_NPC, ID_EX_A, ID_EX_B, ID_EX_IMM, ID_EX_IR;
reg [31:0] EX_MEM_ALUOUT, EX_MEM_B, EX_MEM_IR;
reg [31:0] MEM_WB_LMD, MEM_WB_ALUOUT, MEM_WB_IR;

// ** Instruction Fetch unit ** // 
always @(posedge clk1) begin
    if(HALTED == 0)
    begin
    if(((EX_MEM_IR[31:26] == BEQZ) && (EX_MEM_COND == 1)) ||
        ((EX_MEM_IR[31:26] == BNEQZ) && (EX_MEM_COND == 0)))
    begin
        IF_ID_IR <= #2 mem[EX_MEM_ALUOUT];
        TAKEN_BRANCH <= #2 1;
        IF_ID_NPC <= #2 EX_MEM_ALUOUT + 1;
        PC <= #2 EX_MEM_ALUOUT + 1;
    end
    else
    begin
        IF_ID_IR <= #2 mem[PC];
        IF_ID_NPC <= #2 PC +1;
        PC <= #2 PC +1;
    end
    end
end

// ** Instruction Decode unit ** //
always @(posedge clk2) begin
    if(HALTED == 0)
    begin
    ID_EX_NPC <= #2 IF_ID_NPC;
    ID_EX_A <= #2 reg_bank[IF_ID_IR[25:21]];
    ID_EX_B <= #2 reg_bank[IF_ID_IR[20:16]];
    ID_EX_IMM <= #2 {{16{IF_ID_IR[15]}}, {IF_ID_IR[15:0]}};
    ID_EX_IR <= #2 IF_ID_IR;
    case (IF_ID_IR[31:26])
        ADD, SUB, AND, OR, SLT, MUL: ID_EX_TYPE <= #2 RR_ALU;
        ADDI, SUBI, SLTI: ID_EX_TYPE <= #2 RM_ALU;
        LW: ID_EX_TYPE <= #2 LOAD;
        SW: ID_EX_TYPE <= #2 STORE;
        BNEQZ, BEQZ: ID_EX_TYPE <= #2 BRANCH;
        HLT: ID_EX_TYPE <= #2 HALT;
        default: ID_EX_TYPE <= HALT;
    endcase
    end
end

// ** Execute unit ** //
always @(posedge clk1) begin
    if(HALTED == 0)
    begin
    EX_MEM_TYPE <= #2 ID_EX_TYPE;
    EX_MEM_IR <= #2 ID_EX_IR;
    TAKEN_BRANCH <= #2 0;
    case (ID_EX_TYPE)
        RR_ALU : begin
            case (ID_EX_IR[31:26])
                ADD : EX_MEM_ALUOUT <= #2 ID_EX_A + ID_EX_B;
                SUB : EX_MEM_ALUOUT <= #2 ID_EX_A - ID_EX_B;
                MUL : EX_MEM_ALUOUT <= #2 ID_EX_A * ID_EX_B;
                AND : EX_MEM_ALUOUT <= #2 ID_EX_A & ID_EX_B;
                OR  : EX_MEM_ALUOUT <= #2 ID_EX_A | ID_EX_B;
                SLT : EX_MEM_ALUOUT <= #2 ID_EX_A < ID_EX_B;
                default: EX_MEM_ALUOUT <= #2 32'HX;
            endcase
        end
        RM_ALU: begin
            case (ID_EX_IR[31:26])
                ADDI: EX_MEM_ALUOUT <= #2 ID_EX_A + ID_EX_IMM;
                SUBI: EX_MEM_ALUOUT <= #2 ID_EX_A - ID_EX_IMM;
                SLTI: EX_MEM_ALUOUT <= #2 ID_EX_A < ID_EX_IMM;
                default: EX_MEM_ALUOUT <= #2 32'hx;
            endcase
        end
        LOAD, STORE :begin
            EX_MEM_ALUOUT <= #2 ID_EX_A +ID_EX_IMM;
            EX_MEM_B <= #2 ID_EX_B;
        end
        BRANCH: begin
            EX_MEM_ALUOUT <= #2 ID_EX_NPC + ID_EX_IMM;
            EX_MEM_COND <= #2 (ID_EX_A == 0);
        end
    endcase
    end
end

// ** Memory unit ** //
always @(posedge clk2) begin
    if (HALTED == 0)
    begin
    MEM_WB_TYPE <= #2 EX_MEM_TYPE;
    MEM_WB_IR <= #2 EX_MEM_IR;

    case (EX_MEM_TYPE)
        RR_ALU, RM_ALU: MEM_WB_ALUOUT <= #2 EX_MEM_ALUOUT;
        LOAD: MEM_WB_LMD <= #2 mem[EX_MEM_ALUOUT];
        STORE:if (TAKEN_BRANCH == 0) mem[EX_MEM_ALUOUT] <= #2 EX_MEM_B;
    endcase
    end
end

// ** Register Writeback ** //
always @(posedge clk1) begin
    if(TAKEN_BRANCH == 0) begin
        case (MEM_WB_TYPE)
            RR_ALU: reg_bank[MEM_WB_IR[15:11]] <= #2 MEM_WB_ALUOUT;
            RM_ALU: reg_bank[MEM_WB_IR[20:16]] <= #2 MEM_WB_ALUOUT;
            LOAD:   reg_bank[MEM_WB_IR[20:16]] <= #2 MEM_WB_LMD;
            HALT:   HALTED <= #2 1'B1;
        endcase
    end
end
endmodule

Load store testbench/MIPS_load_type.v
`timescale 1ns/1ps
`include "MIPS.v"
module DUT();
reg clk1, clk2;
integer i;
MIPS m1(
    .clk1(clk1),
    .clk2(clk2)
);
initial begin
    $dumpfile("MIPS_load_type.vcd");
    $dumpvars(0, DUT);
    #300 $finish;
end
initial begin
    clk1 = 0; clk2 = 0; m1.mem[120] = 32'h00000011;
    m1.PC = 0; m1.HALTED = 0;
    repeat (20) begin
        #5 clk1 = 1; #5 clk1 = 0;
        #5 clk2 = 1; #5 clk2 = 0;
    end
end
initial begin
    for(i = 0; i<32; i = i+1) begin
        m1.reg_bank[i] <= i;
    end
    m1.mem[0] = 32'h28010078;
    m1.mem[1] = 32'h0CE77800;
    m1.mem[2] = 32'h0CE77800;
    m1.mem[3] = 32'h0CE77800;
    m1.mem[4] = 32'h20220000;
    m1.mem[5] = 32'h0CE77800;
    m1.mem[6] = 32'h0CE77800;
    m1.mem[7] = 32'h0CE77800;
    m1.mem[8] = 32'h24220001;
    m1.mem[9] = 32'hFC000000;
    #280;
    $display("R1 = %3d, R2 = %d", m1.reg_bank[1], m1.reg_bank[2]);
    $display("The content of 120 address is = %d and of 121 = %d", m1.mem[120], m1.mem[121]);
end
endmodule

Load store testbench/MIPS_load_type.vcd
$date
	Sat Aug 23 16:53:14 2025
$end
$version
	Icarus Verilog
$end
$timescale
	1ps
$end
$scope module DUT $end
$var reg 1 ! clk1 $end
$var reg 1 " clk2 $end
$var integer 32 # i [31:0] $end
$scope module m1 $end
$var wire 1 ! clk1 $end
$var wire 1 " clk2 $end
$var parameter 6 $ ADD $end
$var parameter 6 % ADDI $end
$var parameter 6 & AND $end
$var parameter 6 ' BEQZ $end
$var parameter 6 ( BNEQZ $end
$var parameter 3 ) BRANCH $end
$var parameter 3 * HALT $end
$var parameter 6 + HLT $end
$var parameter 3 , LOAD $end
$var parameter 6 - LW $end
$var parameter 6 . MUL $end
$var parameter 6 / OR $end
$var parameter 3 0 RM_ALU $end
$var parameter 3 1 RR_ALU $end
$var parameter 6 2 SLT $end
$var parameter 6 3 SLTI $end
$var parameter 3 4 STORE $end
$var parameter 6 5 SUB $end
$var parameter 6 6 SUBI $end
$var parameter 6 7 SW $end
$var reg 32 8 EX_MEM_ALUOUT [31:0] $end
$var reg 32 9 EX_MEM_B [31:0] $end
$var reg 1 : EX_MEM_COND $end
$var reg 32 ; EX_MEM_IR [31:0] $end
$var reg 3 < EX_MEM_TYPE [2:0] $end
$var reg 1 = HALTED $end
$var reg 32 > ID_EX_A [31:0] $end
$var reg 32 ? ID_EX_B [31:0] $end
$var reg 32 @ ID_EX_IMM [31:0] $end
$var reg 32 A ID_EX_IR [31:0] $end
$var reg 32 B ID_EX_NPC [31:0] $end
$var reg 3 C ID_EX_TYPE [2:0] $end
$var reg 32 D IF_ID_IR [31:0] $end
$var reg 32 E IF_ID_NPC [31:0] $end
$var reg 32 F MEM_WB_ALUOUT [31:0] $end
$var reg 32 G MEM_WB_IR [31:0] $end
$var reg 32 H MEM_WB_LMD [31:0] $end
$var reg 3 I MEM_WB_TYPE [2:0] $end
$var reg 32 J PC [31:0] $end
$var reg 1 K TAKEN_BRANCH $end
$upscope $end
$upscope $end
$enddefinitions $end
$comment Show the parameter values. $end
$dumpall
b1001 7
b1011 6
b1 5
b11 4
b1100 3
b100 2
b0 1
b1 0
b11 /
b101 .
b1000 -
b10 ,
b111111 +
b101 *
b100 )
b1101 (
b1110 '
b10 &
b1010 %
b0 $
$end
#0
$dumpvars
xK
b0 J
bx I
bx H
bx G
bx F
bx E
bx D
bx C
bx B
bx A
bx @
bx ?
bx >
0=
bx <
bx ;
x:
bx 9
bx 8
b100000 #
0"
0!
$end
#5000
1!
#7000
b1 J
b1 E
b101000000000010000000001111000 D
0K
#10000
0!
#15000
1"
#17000
b1 C
b101000000000010000000001111000 A
b1111000 @
b1 ?
b0 >
b1 B
#20000
0"
#25000
1!
#27000
b1111000 8
b101000000000010000000001111000 ;
b1 <
b10 J
b10 E
b1100111001110111100000000000 D
#30000
0!
#35000
1"
#37000
b1111000 F
b101000000000010000000001111000 G
b1 I
b0 C
b1100111001110111100000000000 A
b111100000000000 @
b111 ?
b111 >
b10 B
#40000
0"
#45000
1!
#47000
b11 J
b11 E
b111 8
b1100111001110111100000000000 ;
b0 <
#50000
0!
#55000
1"
#57000
b11 B
b111 F
b1100111001110111100000000000 G
b0 I
#60000
0"
#65000
1!
#67000
b100 J
b100 E
#70000
0!
#75000
1"
#77000
b100 B
#80000
0"
#85000
1!
#87000
b101 J
b101 E
b100000001000100000000000000000 D
#90000
0!
#95000
1"
#97000
b10 C
b100000001000100000000000000000 A
b0 @
b10 ?
b1111000 >
b101 B
#100000
0"
#105000
1!
#107000
b10 9
b1111000 8
b100000001000100000000000000000 ;
b10 <
b110 J
b110 E
b1100111001110111100000000000 D
#110000
0!
#115000
1"
#117000
b10001 H
b100000001000100000000000000000 G
b10 I
b0 C
b1100111001110111100000000000 A
b111100000000000 @
b111 ?
b111 >
b110 B
#120000
0"
#125000
1!
#127000
b111 J
b111 E
b111 8
b1100111001110111100000000000 ;
b0 <
#130000
0!
#135000
1"
#137000
b111 B
b1100111001110111100000000000 G
b0 I
#140000
0"
#145000
1!
#147000
b1000 J
b1000 E
#150000
0!
#155000
1"
#157000
b1000 B
#160000
0"
#165000
1!
#167000
b1001 J
b1001 E
b100100001000100000000000000001 D
#170000
0!
#175000
1"
#177000
b11 C
b100100001000100000000000000001 A
b1 @
b10001 ?
b1111000 >
b1001 B
#180000
0"
#185000
1!
#187000
b10001 9
b1111001 8
b100100001000100000000000000001 ;
b11 <
b1010 J
b1010 E
b11111100000000000000000000000000 D
#190000
0!
#195000
1"
#197000
b100100001000100000000000000001 G
b11 I
b101 C
b11111100000000000000000000000000 A
b0 @
b0 ?
b0 >
b1010 B
#200000
0"
#205000
1!
#207000
b1011 J
b1011 E
bx D
b11111100000000000000000000000000 ;
b101 <
#210000
0!
#215000
1"
#217000
bx A
bx @
bx ?
bx >
b1011 B
b11111100000000000000000000000000 G
b101 I
#220000
0"
#225000
1!
#227000
1=
bx ;
b1100 J
b1100 E
