Verilog code of processor/MIPS.v
module MIPS(
    input clk1,
    input clk2
);
parameter 
ADD = 6'b000000,
SUB = 6'b000001,
AND = 6'b000010,
OR = 6'b000011,
SLT = 6'b000100,
MUL = 6'b000101,
HLT = 6'b111111,

LW = 6'b001000,
SW = 6'b001001,
ADDI = 6'b001010,
SUBI = 6'b001011,
SLTI = 6'b001100,
BNEQZ = 6'b001101,
BEQZ = 6'b001110;

parameter
    RR_ALU = 3'B000,
    RM_ALU = 3'B001,
    LOAD = 3'B010,
    STORE = 3'B011,
    BRANCH = 3'B100,
    HALT = 3'B101;

reg TAKEN_BRANCH, HALTED;

reg [31:0] reg_bank [0:31];
reg [31:0] mem [0:1023];

reg EX_MEM_COND;
reg [2:0] ID_EX_TYPE, EX_MEM_TYPE, MEM_WB_TYPE;
reg [31:0] PC, IF_ID_NPC, IF_ID_IR;
reg [31:0] ID_EX_NPC, ID_EX_A, ID_EX_B, ID_EX_IMM, ID_EX_IR;
reg [31:0] EX_MEM_ALUOUT, EX_MEM_B, EX_MEM_IR;
reg [31:0] MEM_WB_LMD, MEM_WB_ALUOUT, MEM_WB_IR;

// ** Instruction Fetch unit ** // 
always @(posedge clk1) begin
    if(HALTED == 0)
    begin
    if(((EX_MEM_IR[31:26] == BEQZ) && (EX_MEM_COND == 1)) ||
        ((EX_MEM_IR[31:26] == BNEQZ) && (EX_MEM_COND == 0)))
    begin
        IF_ID_IR <= #2 mem[EX_MEM_ALUOUT];
        TAKEN_BRANCH <= #2 1;
        IF_ID_NPC <= #2 EX_MEM_ALUOUT + 1;
        PC <= #2 EX_MEM_ALUOUT + 1;
    end
    else
    begin
        IF_ID_IR <= #2 mem[PC];
        IF_ID_NPC <= #2 PC +1;
        PC <= #2 PC +1;
    end
    end
end

// ** Instruction Decode unit ** //
always @(posedge clk2) begin
    if(HALTED == 0)
    begin
    ID_EX_NPC <= #2 IF_ID_NPC;
    ID_EX_A <= #2 reg_bank[IF_ID_IR[25:21]];
    ID_EX_B <= #2 reg_bank[IF_ID_IR[20:16]];
    ID_EX_IMM <= #2 {{16{IF_ID_IR[15]}}, {IF_ID_IR[15:0]}};
    ID_EX_IR <= #2 IF_ID_IR;
    case (IF_ID_IR[31:26])
        ADD, SUB, AND, OR, SLT, MUL: ID_EX_TYPE <= #2 RR_ALU;
        ADDI, SUBI, SLTI: ID_EX_TYPE <= #2 RM_ALU;
        LW: ID_EX_TYPE <= #2 LOAD;
        SW: ID_EX_TYPE <= #2 STORE;
        BNEQZ, BEQZ: ID_EX_TYPE <= #2 BRANCH;
        HLT: ID_EX_TYPE <= #2 HALT;
        default: ID_EX_TYPE <= HALT;
    endcase
    end
end

// ** Execute unit ** //
always @(posedge clk1) begin
    if(HALTED == 0)
    begin
    EX_MEM_TYPE <= #2 ID_EX_TYPE;
    EX_MEM_IR <= #2 ID_EX_IR;
    TAKEN_BRANCH <= #2 0;
    case (ID_EX_TYPE)
        RR_ALU : begin
            case (ID_EX_IR[31:26])
                ADD : EX_MEM_ALUOUT <= #2 ID_EX_A + ID_EX_B;
                SUB : EX_MEM_ALUOUT <= #2 ID_EX_A - ID_EX_B;
                MUL : EX_MEM_ALUOUT <= #2 ID_EX_A * ID_EX_B;
                AND : EX_MEM_ALUOUT <= #2 ID_EX_A & ID_EX_B;
                OR  : EX_MEM_ALUOUT <= #2 ID_EX_A | ID_EX_B;
                SLT : EX_MEM_ALUOUT <= #2 ID_EX_A < ID_EX_B;
                default: EX_MEM_ALUOUT <= #2 32'HX;
            endcase
        end
        RM_ALU: begin
            case (ID_EX_IR[31:26])
                ADDI: EX_MEM_ALUOUT <= #2 ID_EX_A + ID_EX_IMM;
                SUBI: EX_MEM_ALUOUT <= #2 ID_EX_A - ID_EX_IMM;
                SLTI: EX_MEM_ALUOUT <= #2 ID_EX_A < ID_EX_IMM;
                default: EX_MEM_ALUOUT <= #2 32'hx;
            endcase
        end
        LOAD, STORE :begin
            EX_MEM_ALUOUT <= #2 ID_EX_A +ID_EX_IMM;
            EX_MEM_B <= #2 ID_EX_B;
        end
        BRANCH: begin
            EX_MEM_ALUOUT <= #2 ID_EX_NPC + ID_EX_IMM;
            EX_MEM_COND <= #2 (ID_EX_A == 0);
        end
    endcase
    end
end

// ** Memory unit ** //
always @(posedge clk2) begin
    if (HALTED == 0)
    begin
    MEM_WB_TYPE <= #2 EX_MEM_TYPE;
    MEM_WB_IR <= #2 EX_MEM_IR;

    case (EX_MEM_TYPE)
        RR_ALU, RM_ALU: MEM_WB_ALUOUT <= #2 EX_MEM_ALUOUT;
        LOAD: MEM_WB_LMD <= #2 mem[EX_MEM_ALUOUT];
        STORE:if (TAKEN_BRANCH == 0) mem[EX_MEM_ALUOUT] <= #2 EX_MEM_B;
    endcase
    end
end

// ** Register Writeback ** //
always @(posedge clk1) begin
    if(TAKEN_BRANCH == 0) begin
        case (MEM_WB_TYPE)
            RR_ALU: reg_bank[MEM_WB_IR[15:11]] <= #2 MEM_WB_ALUOUT;
            RM_ALU: reg_bank[MEM_WB_IR[20:16]] <= #2 MEM_WB_ALUOUT;
            LOAD:   reg_bank[MEM_WB_IR[20:16]] <= #2 MEM_WB_LMD;
            HALT:   HALTED <= #2 1'B1;
        endcase
    end
end
endmodule

Arithmatic testbench/MIPS_test.v
`timescale 1ns/1ps
`include "MIPS.v"
module DUT();
reg clk1, clk2;
integer i, k;
MIPS m1(
    .clk1(clk1),
    .clk2(clk2)
);
initial begin
    clk1 = 0; clk2 = 0;
    repeat (20) begin
        #5 clk1 = 1; #5 clk1 = 0;
        #5 clk2 = 1; #5 clk2 = 0;
    end
end
initial begin
    $dumpfile("MIPS_test.vcd");
    $dumpvars(0,DUT);

    #300 $finish;
end
initial begin
    for(k = 0; k<32; k = k+1)begin
        m1.reg_bank[k] = k;
    end
    m1.mem[0] = 32'h2801000A;
    m1.mem[1] = 32'h28020014;
    m1.mem[2] = 32'h28030019;
    m1.mem[3] = 32'h0CE77800;
    m1.mem[4] = 32'h0CE77800;
    m1.mem[5] = 32'h00222000;
    m1.mem[6] = 32'h0CE77800;
    m1.mem[7] = 32'h00832800;
    m1.mem[8] = 32'hFC000000;

    m1.HALTED = 0;
    m1.PC = 0;
    m1.TAKEN_BRANCH = 0;

    #280
    for(i = 0; i<6; i++)
    $display("R%d - %2d", i, m1.reg_bank[i]);
end
endmodule

Arithmatic testbench/MIPS_test.vcd
$date
	Sat Aug 23 09:20:10 2025
$end
$version
	Icarus Verilog
$end
$timescale
	1ps
$end
$scope module DUT $end
$var reg 1 ! clk1 $end
$var reg 1 " clk2 $end
$var integer 32 # i [31:0] $end
$var integer 32 $ k [31:0] $end
$scope module m1 $end
$var wire 1 ! clk1 $end
$var wire 1 " clk2 $end
$var parameter 6 % ADD $end
$var parameter 6 & ADDI $end
$var parameter 6 ' AND $end
$var parameter 6 ( BEQZ $end
$var parameter 6 ) BNEQZ $end
$var parameter 3 * BRANCH $end
$var parameter 3 + HALT $end
$var parameter 6 , HLT $end
$var parameter 3 - LOAD $end
$var parameter 6 . LW $end
$var parameter 6 / MUL $end
$var parameter 6 0 OR $end
$var parameter 3 1 RM_ALU $end
$var parameter 3 2 RR_ALU $end
$var parameter 6 3 SLT $end
$var parameter 6 4 SLTI $end
$var parameter 3 5 STORE $end
$var parameter 6 6 SUB $end
$var parameter 6 7 SUBI $end
$var parameter 6 8 SW $end
$var reg 32 9 EX_MEM_ALUOUT [31:0] $end
$var reg 32 : EX_MEM_B [31:0] $end
$var reg 1 ; EX_MEM_COND $end
$var reg 32 < EX_MEM_IR [31:0] $end
$var reg 3 = EX_MEM_TYPE [2:0] $end
$var reg 1 > HALTED $end
$var reg 32 ? ID_EX_A [31:0] $end
$var reg 32 @ ID_EX_B [31:0] $end
$var reg 32 A ID_EX_IMM [31:0] $end
$var reg 32 B ID_EX_IR [31:0] $end
$var reg 32 C ID_EX_NPC [31:0] $end
$var reg 3 D ID_EX_TYPE [2:0] $end
$var reg 32 E IF_ID_IR [31:0] $end
$var reg 32 F IF_ID_NPC [31:0] $end
$var reg 32 G MEM_WB_ALUOUT [31:0] $end
$var reg 32 H MEM_WB_IR [31:0] $end
$var reg 32 I MEM_WB_LMD [31:0] $end
$var reg 3 J MEM_WB_TYPE [2:0] $end
$var reg 32 K PC [31:0] $end
$var reg 1 L TAKEN_BRANCH $end
$upscope $end
$upscope $end
$enddefinitions $end
$comment Show the parameter values. $end
$dumpall
b1001 8
b1011 7
b1 6
b11 5
b1100 4
b100 3
b0 2
b1 1
b11 0
b101 /
b1000 .
b10 -
b111111 ,
b101 +
b100 *
b1101 )
b1110 (
b10 '
b1010 &
b0 %
$end
#0
$dumpvars
0L
b0 K
bx J
bx I
bx H
bx G
bx F
bx E
bx D
bx C
bx B
bx A
bx @
bx ?
0>
bx =
bx <
x;
bx :
bx 9
b100000 $
bx #
0"
0!
$end
#5000
1!
#7000
b1 K
b1 F
b101000000000010000000000001010 E
#10000
0!
#15000
1"
#17000
b1 D
b101000000000010000000000001010 B
b1010 A
b1 @
b0 ?
b1 C
#20000
0"
#25000
1!
#27000
b1010 9
b101000000000010000000000001010 <
b1 =
b10 K
b10 F
b101000000000100000000000010100 E
#30000
0!
#35000
1"
#37000
b1010 G
b101000000000010000000000001010 H
b1 J
b101000000000100000000000010100 B
b10100 A
b10 @
b10 C
#40000
0"
#45000
1!
#47000
b11 K
b11 F
b101000000000110000000000011001 E
b10100 9
b101000000000100000000000010100 <
#50000
0!
#55000
1"
#57000
b101000000000110000000000011001 B
b11001 A
b11 @
b11 C
b10100 G
b101000000000100000000000010100 H
#60000
0"
#65000
1!
#67000
b11001 9
b101000000000110000000000011001 <
b100 K
b100 F
b1100111001110111100000000000 E
#70000
0!
#75000
1"
#77000
b11001 G
b101000000000110000000000011001 H
b0 D
b1100111001110111100000000000 B
b111100000000000 A
b111 @
b111 ?
b100 C
#80000
0"
#85000
1!
#87000
b101 K
b101 F
b111 9
b1100111001110111100000000000 <
b0 =
#90000
0!
#95000
1"
#97000
b101 C
b111 G
b1100111001110111100000000000 H
b0 J
#100000
0"
#105000
1!
#107000
b110 K
b110 F
b1000100010000000000000 E
#110000
0!
#115000
1"
#117000
b1000100010000000000000 B
b10000000000000 A
b10100 @
b1010 ?
b110 C
#120000
0"
#125000
1!
#127000
b111 K
b111 F
b1100111001110111100000000000 E
b11110 9
b1000100010000000000000 <
#130000
0!
#135000
1"
#137000
b1100111001110111100000000000 B
b111100000000000 A
b111 @
b111 ?
b111 C
b11110 G
b1000100010000000000000 H
#140000
0"
#145000
1!
#147000
b111 9
b1100111001110111100000000000 <
b1000 K
b1000 F
b100000110010100000000000 E
#150000
0!
#155000
1"
#157000
b111 G
b1100111001110111100000000000 H
b100000110010100000000000 B
b10100000000000 A
b11001 @
b11110 ?
b1000 C
#160000
0"
#165000
1!
#167000
b1001 K
b1001 F
b11111100000000000000000000000000 E
b110111 9
b100000110010100000000000 <
#170000
0!
#175000
1"
#177000
b101 D
b11111100000000000000000000000000 B
b0 A
b0 @
b0 ?
b1001 C
b110111 G
b100000110010100000000000 H
#180000
0"
#185000
1!
#187000
b11111100000000000000000000000000 <
b101 =
b1010 K
b1010 F
bx E
#190000
0!
#195000
1"
#197000
b11111100000000000000000000000000 H
b101 J
bx B
bx A
bx @
bx ?
b1010 C
#200000
0"
#205000
1!
#207000
b1011 K
b1011 F
bx <
1>
#210000
0!
#215000
1"
#220000
0"
#225000
1!
#230000
0!
#235000
1"
#240000
0"
#245000
1!
#250000
0!
#255000
1"
#260000
0"
#265000
1!
#270000
0!
#275000
1"
#280000
0"
b110 #
