Verilog code of processor/MIPS.v
module MIPS(
    input clk1,
    input clk2
);
parameter 
ADD = 6'b000000,
SUB = 6'b000001,
AND = 6'b000010,
OR = 6'b000011,
SLT = 6'b000100,
MUL = 6'b000101,
HLT = 6'b111111,

LW = 6'b001000,
SW = 6'b001001,
ADDI = 6'b001010,
SUBI = 6'b001011,
SLTI = 6'b001100,
BNEQZ = 6'b001101,
BEQZ = 6'b001110;

parameter
    RR_ALU = 3'B000,
    RM_ALU = 3'B001,
    LOAD = 3'B010,
    STORE = 3'B011,
    BRANCH = 3'B100,
    HALT = 3'B101;

reg TAKEN_BRANCH, HALTED;

reg [31:0] reg_bank [0:31];
reg [31:0] mem [0:1023];

reg EX_MEM_COND;
reg [2:0] ID_EX_TYPE, EX_MEM_TYPE, MEM_WB_TYPE;
reg [31:0] PC, IF_ID_NPC, IF_ID_IR;
reg [31:0] ID_EX_NPC, ID_EX_A, ID_EX_B, ID_EX_IMM, ID_EX_IR;
reg [31:0] EX_MEM_ALUOUT, EX_MEM_B, EX_MEM_IR;
reg [31:0] MEM_WB_LMD, MEM_WB_ALUOUT, MEM_WB_IR;

// ** Instruction Fetch unit ** // 
always @(posedge clk1) begin
    if(HALTED == 0)
    begin
    if(((EX_MEM_IR[31:26] == BEQZ) && (EX_MEM_COND == 1)) ||
        ((EX_MEM_IR[31:26] == BNEQZ) && (EX_MEM_COND == 0)))
    begin
        IF_ID_IR <= #2 mem[EX_MEM_ALUOUT];
        TAKEN_BRANCH <= #2 1;
        IF_ID_NPC <= #2 EX_MEM_ALUOUT + 1;
        PC <= #2 EX_MEM_ALUOUT + 1;
    end
    else
    begin
        IF_ID_IR <= #2 mem[PC];
        IF_ID_NPC <= #2 PC +1;
        PC <= #2 PC +1;
    end
    end
end

// ** Instruction Decode unit ** //
always @(posedge clk2) begin
    if(HALTED == 0)
    begin
    ID_EX_NPC <= #2 IF_ID_NPC;
    ID_EX_A <= #2 reg_bank[IF_ID_IR[25:21]];
    ID_EX_B <= #2 reg_bank[IF_ID_IR[20:16]];
    ID_EX_IMM <= #2 {{16{IF_ID_IR[15]}}, {IF_ID_IR[15:0]}};
    ID_EX_IR <= #2 IF_ID_IR;
    case (IF_ID_IR[31:26])
        ADD, SUB, AND, OR, SLT, MUL: ID_EX_TYPE <= #2 RR_ALU;
        ADDI, SUBI, SLTI: ID_EX_TYPE <= #2 RM_ALU;
        LW: ID_EX_TYPE <= #2 LOAD;
        SW: ID_EX_TYPE <= #2 STORE;
        BNEQZ, BEQZ: ID_EX_TYPE <= #2 BRANCH;
        HLT: ID_EX_TYPE <= #2 HALT;
        default: ID_EX_TYPE <= HALT;
    endcase
    end
end

// ** Execute unit ** //
always @(posedge clk1) begin
    if(HALTED == 0)
    begin
    EX_MEM_TYPE <= #2 ID_EX_TYPE;
    EX_MEM_IR <= #2 ID_EX_IR;
    TAKEN_BRANCH <= #2 0;
    case (ID_EX_TYPE)
        RR_ALU : begin
            case (ID_EX_IR[31:26])
                ADD : EX_MEM_ALUOUT <= #2 ID_EX_A + ID_EX_B;
                SUB : EX_MEM_ALUOUT <= #2 ID_EX_A - ID_EX_B;
                MUL : EX_MEM_ALUOUT <= #2 ID_EX_A * ID_EX_B;
                AND : EX_MEM_ALUOUT <= #2 ID_EX_A & ID_EX_B;
                OR  : EX_MEM_ALUOUT <= #2 ID_EX_A | ID_EX_B;
                SLT : EX_MEM_ALUOUT <= #2 ID_EX_A < ID_EX_B;
                default: EX_MEM_ALUOUT <= #2 32'HX;
            endcase
        end
        RM_ALU: begin
            case (ID_EX_IR[31:26])
                ADDI: EX_MEM_ALUOUT <= #2 ID_EX_A + ID_EX_IMM;
                SUBI: EX_MEM_ALUOUT <= #2 ID_EX_A - ID_EX_IMM;
                SLTI: EX_MEM_ALUOUT <= #2 ID_EX_A < ID_EX_IMM;
                default: EX_MEM_ALUOUT <= #2 32'hx;
            endcase
        end
        LOAD, STORE :begin
            EX_MEM_ALUOUT <= #2 ID_EX_A +ID_EX_IMM;
            EX_MEM_B <= #2 ID_EX_B;
        end
        BRANCH: begin
            EX_MEM_ALUOUT <= #2 ID_EX_NPC + ID_EX_IMM;
            EX_MEM_COND <= #2 (ID_EX_A == 0);
        end
    endcase
    end
end

// ** Memory unit ** //
always @(posedge clk2) begin
    if (HALTED == 0)
    begin
    MEM_WB_TYPE <= #2 EX_MEM_TYPE;
    MEM_WB_IR <= #2 EX_MEM_IR;

    case (EX_MEM_TYPE)
        RR_ALU, RM_ALU: MEM_WB_ALUOUT <= #2 EX_MEM_ALUOUT;
        LOAD: MEM_WB_LMD <= #2 mem[EX_MEM_ALUOUT];
        STORE:if (TAKEN_BRANCH == 0) mem[EX_MEM_ALUOUT] <= #2 EX_MEM_B;
    endcase
    end
end

// ** Register Writeback ** //
always @(posedge clk1) begin
    if(TAKEN_BRANCH == 0) begin
        case (MEM_WB_TYPE)
            RR_ALU: reg_bank[MEM_WB_IR[15:11]] <= #2 MEM_WB_ALUOUT;
            RM_ALU: reg_bank[MEM_WB_IR[20:16]] <= #2 MEM_WB_ALUOUT;
            LOAD:   reg_bank[MEM_WB_IR[20:16]] <= #2 MEM_WB_LMD;
            HALT:   HALTED <= #2 1'B1;
        endcase
    end
end
endmodule

Factroial calculation using processor/MIPS_factorial_calculation.v
`timescale 1ns/1ps
`include "MIPS.v"
module DUT();
reg clk1, clk2;
integer i;
MIPS m1(
    .clk1(clk1),
    .clk2(clk2)
);
initial begin
    $dumpfile("MIPS_factorial.vcd");
    $dumpvars(0, DUT);
    #5000 $finish;
end
initial begin
    clk1 = 0; clk2 = 0; m1.PC = 0; m1.HALTED = 0; m1.mem[200] = 6;
end
always begin
        #5 clk1 = 1; #5 clk1 = 0;
        #5 clk2 = 1; #5 clk2 = 0;
end
initial begin
    for(i = 0; i<32; i = i+1) begin
        m1.reg_bank[i] = i;
    end
    m1.mem[0] = 32'h280100C8;
    m1.mem[1] = 32'h28030001;

    m1.mem[2] = 32'h0CE77800;
    m1.mem[3] = 32'h0CE77800;

    m1.mem[4] = 32'h20220000;

    m1.mem[5] = 32'h0CE77800;
    m1.mem[6] = 32'h0CE77800;
    m1.mem[7] = 32'h0CE77800;

    m1.mem[8] = 32'h14431800;
    m1.mem[9] = 32'h2C420001;

    m1.mem[10] = 32'h0CE77800;
    m1.mem[11] = 32'h0CE77800;

    m1.mem[12] = 32'h3440FFFB;

    m1.mem[13] = 32'h0CE77800;
    m1.mem[14] = 32'h0CE77800;
    m1.mem[15] = 32'h2423FFFE;
    m1.mem[16] = 32'hFC000000;
end
initial begin
$monitor("R1 = %d, R2 = %d, R3 = %d, TIME: = ",m1.reg_bank[1], m1.reg_bank[2], m1.reg_bank[3],$time);
#2000 $display("content in 198", m1.mem[198]);
end
endmodule

Factroial calculation using processor/MIPS_factorial.vcd
$date
	Sat Aug 23 20:20:11 2025
$end
$version
	Icarus Verilog
$end
$timescale
	1ps
$end
$scope module DUT $end
$var reg 1 ! clk1 $end
$var reg 1 " clk2 $end
$var integer 32 # i [31:0] $end
$scope module m1 $end
$var wire 1 ! clk1 $end
$var wire 1 " clk2 $end
$var parameter 6 $ ADD $end
$var parameter 6 % ADDI $end
$var parameter 6 & AND $end
$var parameter 6 ' BEQZ $end
$var parameter 6 ( BNEQZ $end
$var parameter 3 ) BRANCH $end
$var parameter 3 * HALT $end
$var parameter 6 + HLT $end
$var parameter 3 , LOAD $end
$var parameter 6 - LW $end
$var parameter 6 . MUL $end
$var parameter 6 / OR $end
$var parameter 3 0 RM_ALU $end
$var parameter 3 1 RR_ALU $end
$var parameter 6 2 SLT $end
$var parameter 6 3 SLTI $end
$var parameter 3 4 STORE $end
$var parameter 6 5 SUB $end
$var parameter 6 6 SUBI $end
$var parameter 6 7 SW $end
$var reg 32 8 EX_MEM_ALUOUT [31:0] $end
$var reg 32 9 EX_MEM_B [31:0] $end
$var reg 1 : EX_MEM_COND $end
$var reg 32 ; EX_MEM_IR [31:0] $end
$var reg 3 < EX_MEM_TYPE [2:0] $end
$var reg 1 = HALTED $end
$var reg 32 > ID_EX_A [31:0] $end
$var reg 32 ? ID_EX_B [31:0] $end
$var reg 32 @ ID_EX_IMM [31:0] $end
$var reg 32 A ID_EX_IR [31:0] $end
$var reg 32 B ID_EX_NPC [31:0] $end
$var reg 3 C ID_EX_TYPE [2:0] $end
$var reg 32 D IF_ID_IR [31:0] $end
$var reg 32 E IF_ID_NPC [31:0] $end
$var reg 32 F MEM_WB_ALUOUT [31:0] $end
$var reg 32 G MEM_WB_IR [31:0] $end
$var reg 32 H MEM_WB_LMD [31:0] $end
$var reg 3 I MEM_WB_TYPE [2:0] $end
$var reg 32 J PC [31:0] $end
$var reg 1 K TAKEN_BRANCH $end
$upscope $end
$upscope $end
$enddefinitions $end
$comment Show the parameter values. $end
$dumpall
b1001 7
b1011 6
b1 5
b11 4
b1100 3
b100 2
b0 1
b1 0
b11 /
b101 .
b1000 -
b10 ,
b111111 +
b101 *
b100 )
b1101 (
b1110 '
b10 &
b1010 %
b0 $
$end
#0
$dumpvars
xK
b0 J
bx I
bx H
bx G
bx F
bx E
bx D
bx C
bx B
bx A
bx @
bx ?
bx >
0=
bx <
bx ;
x:
bx 9
bx 8
b100000 #
0"
0!
$end
#5000
1!
#7000
b1 J
b1 E
b101000000000010000000011001000 D
0K
#10000
0!
#15000
1"
#17000
b1 C
b101000000000010000000011001000 A
b11001000 @
b1 ?
b0 >
b1 B
#20000
0"
#25000
1!
#27000
b11001000 8
b101000000000010000000011001000 ;
b1 <
b10 J
b10 E
b101000000000110000000000000001 D
#30000
0!
#35000
1"
#37000
b11001000 F
b101000000000010000000011001000 G
b1 I
b101000000000110000000000000001 A
b1 @
b11 ?
b10 B
#40000
0"
#45000
1!
#47000
b11 J
b11 E
b1100111001110111100000000000 D
b1 8
b101000000000110000000000000001 ;
#50000
0!
#55000
1"
#57000
b0 C
b1100111001110111100000000000 A
b111100000000000 @
b111 ?
b111 >
b11 B
b1 F
b101000000000110000000000000001 G
#60000
0"
#65000
1!
#67000
b111 8
b1100111001110111100000000000 ;
b0 <
b100 J
b100 E
#70000
0!
#75000
1"
#77000
b111 F
b1100111001110111100000000000 G
b0 I
b100 B
#80000
0"
#85000
1!
#87000
b101 J
b101 E
b100000001000100000000000000000 D
#90000
0!
#95000
1"
#97000
b10 C
b100000001000100000000000000000 A
b0 @
b10 ?
b11001000 >
b101 B
#100000
0"
#105000
1!
#107000
b10 9
b11001000 8
b100000001000100000000000000000 ;
b10 <
b110 J
b110 E
b1100111001110111100000000000 D
#110000
0!
#115000
1"
#117000
b110 H
b100000001000100000000000000000 G
b10 I
b0 C
b1100111001110111100000000000 A
b111100000000000 @
b111 ?
b111 >
b110 B
#120000
0"
#125000
1!
#127000
b111 J
b111 E
b111 8
b1100111001110111100000000000 ;
b0 <
#130000
0!
#135000
1"
#137000
b111 B
b1100111001110111100000000000 G
b0 I
#140000
0"
#145000
1!
#147000
b1000 J
b1000 E
#150000
0!
#155000
1"
#157000
b1000 B
#160000
0"
#165000
1!
#167000
b1001 J
b1001 E
b10100010000110001100000000000 D
#170000
0!
#175000
1"
#177000
b10100010000110001100000000000 A
b1100000000000 @
b1 ?
b110 >
b1001 B
#180000
0"
#185000
1!
#187000
b110 8
b10100010000110001100000000000 ;
b1010 J
b1010 E
b101100010000100000000000000001 D
#190000
0!
#195000
1"
#197000
b110 F
b10100010000110001100000000000 G
b1 C
b101100010000100000000000000001 A
b1 @
b110 ?
b1010 B
#200000
0"
#205000
1!
#207000
b1011 J
b1011 E
b1100111001110111100000000000 D
b101 8
b101100010000100000000000000001 ;
b1 <
#210000
0!
#215000
1"
#217000
b0 C
b1100111001110111100000000000 A
b111100000000000 @
b111 ?
b111 >
b1011 B
b101 F
b101100010000100000000000000001 G
b1 I
#220000
0"
#225000
1!
#227000
b111 8
b1100111001110111100000000000 ;
b0 <
b1100 J
b1100 E
#230000
0!
#235000
1"
#237000
b111 F
b1100111001110111100000000000 G
b0 I
b1100 B
#240000
0"
#245000
1!
#247000
b1101 J
b1101 E
b110100010000001111111111111011 D
#250000
0!
#255000
1"
#257000
b100 C
b110100010000001111111111111011 A
b11111111111111111111111111111011 @
b0 ?
b101 >
b1101 B
#260000
0"
#265000
1!
#267000
0:
b1000 8
b110100010000001111111111111011 ;
b100 <
b1110 J
b1110 E
b1100111001110111100000000000 D
#270000
0!
#275000
1"
#277000
b110100010000001111111111111011 G
b100 I
b0 C
b1100111001110111100000000000 A
b111100000000000 @
b111 ?
b111 >
b1110 B
#280000
0"
#285000
1!
#287000
b1001 J
b1001 E
1K
b10100010000110001100000000000 D
b111 8
b1100111001110111100000000000 ;
b0 <
#290000
0!
#295000
1"
#297000
b10100010000110001100000000000 A
b1100000000000 @
b110 ?
b101 >
b1001 B
b1100111001110111100000000000 G
b0 I
#300000
0"
#305000
1!
#307000
b11110 8
0K
b10100010000110001100000000000 ;
b1010 J
b1010 E
b101100010000100000000000000001 D
#310000
0!
#315000
1"
#317000
b11110 F
b10100010000110001100000000000 G
b1 C
b101100010000100000000000000001 A
b1 @
b101 ?
b1010 B
#320000
0"
#325000
1!
#327000
b1011 J
b1011 E
b1100111001110111100000000000 D
b100 8
b101100010000100000000000000001 ;
b1 <
#330000
0!
#335000
1"
#337000
b0 C
b1100111001110111100000000000 A
b111100000000000 @
b111 ?
b111 >
b1011 B
b100 F
b101100010000100000000000000001 G
b1 I
#340000
0"
#345000
1!
#347000
b111 8
b1100111001110111100000000000 ;
b0 <
b1100 J
b1100 E
#350000
0!
#355000
1"
#357000
b111 F
b1100111001110111100000000000 G
b0 I
b1100 B
#360000
0"
#365000
1!
#367000
b1101 J
b1101 E
b110100010000001111111111111011 D
#370000
0!
#375000
1"
#377000
b100 C
b110100010000001111111111111011 A
b11111111111111111111111111111011 @
b0 ?
b100 >
b1101 B
#380000
0"
#385000
1!
#387000
b1000 8
b110100010000001111111111111011 ;
b100 <
b1110 J
b1110 E
b1100111001110111100000000000 D
#390000
0!
#395000
1"
#397000
b110100010000001111111111111011 G
b100 I
b0 C
b1100111001110111100000000000 A
b111100000000000 @
b111 ?
b111 >
b1110 B
#400000
0"
#405000
1!
#407000
b1001 J
b1001 E
1K
b10100010000110001100000000000 D
b111 8
b1100111001110111100000000000 ;
b0 <
#410000
0!
#415000
1"
#417000
b10100010000110001100000000000 A
b1100000000000 @
b11110 ?
b100 >
b1001 B
b1100111001110111100000000000 G
b0 I
#420000
0"
#425000
1!
#427000
b1111000 8
0K
b10100010000110001100000000000 ;
b1010 J
b1010 E
b101100010000100000000000000001 D
#430000
0!
#435000
1"
#437000
b1111000 F
b10100010000110001100000000000 G
b1 C
b101100010000100000000000000001 A
b1 @
b100 ?
b1010 B
#440000
0"
#445000
1!
#447000
b1011 J
b1011 E
b1100111001110111100000000000 D
b11 8
b101100010000100000000000000001 ;
b1 <
#450000
0!
#455000
1"
#457000
b0 C
b1100111001110111100000000000 A
b111100000000000 @
b111 ?
b111 >
b1011 B
b11 F
b101100010000100000000000000001 G
b1 I
#460000
0"
#465000
1!
#467000
b111 8
b1100111001110111100000000000 ;
b0 <
b1100 J
b1100 E
#470000
0!
#475000
1"
#477000
b111 F
b1100111001110111100000000000 G
b0 I
b1100 B
#480000
0"
#485000
1!
#487000
b1101 J
b1101 E
b110100010000001111111111111011 D
#490000
0!
#495000
1"
#497000
b100 C
b110100010000001111111111111011 A
b11111111111111111111111111111011 @
b0 ?
b11 >
b1101 B
#500000
0"
#505000
1!
#507000
b1000 8
b110100010000001111111111111011 ;
b100 <
b1110 J
b1110 E
b1100111001110111100000000000 D
#510000
0!
#515000
1"
#517000
b110100010000001111111111111011 G
b100 I
b0 C
b1100111001110111100000000000 A
b111100000000000 @
b111 ?
b111 >
b1110 B
#520000
0"
#525000
1!
#527000
b1001 J
b1001 E
1K
b10100010000110001100000000000 D
b111 8
b1100111001110111100000000000 ;
b0 <
#530000
0!
#535000
1"
#537000
b10100010000110001100000000000 A
b1100000000000 @
b1111000 ?
b11 >
b1001 B
b1100111001110111100000000000 G
b0 I
#540000
0"
#545000
1!
#547000
b101101000 8
0K
b10100010000110001100000000000 ;
b1010 J
b1010 E
b101100010000100000000000000001 D
#550000
0!
#555000
1"
#557000
b101101000 F
b10100010000110001100000000000 G
b1 C
b101100010000100000000000000001 A
b1 @
b11 ?
b1010 B
#560000
0"
#565000
1!
#567000
b1011 J
b1011 E
b1100111001110111100000000000 D
b10 8
b101100010000100000000000000001 ;
b1 <
#570000
0!
#575000
1"
#577000
b0 C
b1100111001110111100000000000 A
b111100000000000 @
b111 ?
b111 >
b1011 B
b10 F
b101100010000100000000000000001 G
b1 I
#580000
0"
#585000
1!
#587000
b111 8
b1100111001110111100000000000 ;
b0 <
b1100 J
b1100 E
#590000
0!
#595000
1"
#597000
b111 F
b1100111001110111100000000000 G
b0 I
b1100 B
#600000
0"
#605000
1!
#607000
b1101 J
b1101 E
b110100010000001111111111111011 D
#610000
0!
#615000
1"
#617000
b100 C
b110100010000001111111111111011 A
b11111111111111111111111111111011 @
b0 ?
b10 >
b1101 B
#620000
0"
#625000
1!
#627000
b1000 8
b110100010000001111111111111011 ;
b100 <
b1110 J
b1110 E
b1100111001110111100000000000 D
#630000
0!
#635000
1"
#637000
b110100010000001111111111111011 G
b100 I
b0 C
b1100111001110111100000000000 A
b111100000000000 @
b111 ?
b111 >
b1110 B
#640000
0"
#645000
1!
#647000
b1001 J
b1001 E
1K
b10100010000110001100000000000 D
b111 8
b1100111001110111100000000000 ;
b0 <
#650000
0!
#655000
1"
#657000
b10100010000110001100000000000 A
b1100000000000 @
b101101000 ?
b10 >
b1001 B
b1100111001110111100000000000 G
b0 I
#660000
0"
#665000
1!
#667000
b1011010000 8
0K
b10100010000110001100000000000 ;
b1010 J
b1010 E
b101100010000100000000000000001 D
#670000
0!
#675000
1"
#677000
b1011010000 F
b10100010000110001100000000000 G
b1 C
b101100010000100000000000000001 A
b1 @
b10 ?
b1010 B
#680000
0"
#685000
1!
#687000
b1011 J
b1011 E
b1100111001110111100000000000 D
b1 8
b101100010000100000000000000001 ;
b1 <
#690000
0!
#695000
1"
#697000
b0 C
b1100111001110111100000000000 A
b111100000000000 @
b111 ?
b111 >
b1011 B
b1 F
b101100010000100000000000000001 G
b1 I
#700000
0"
#705000
1!
#707000
b111 8
b1100111001110111100000000000 ;
b0 <
b1100 J
b1100 E
#710000
0!
#715000
1"
#717000
b111 F
b1100111001110111100000000000 G
b0 I
b1100 B
#720000
0"
#725000
1!
#727000
b1101 J
b1101 E
b110100010000001111111111111011 D
#730000
0!
#735000
1"
#737000
b100 C
b110100010000001111111111111011 A
b11111111111111111111111111111011 @
b0 ?
b1 >
b1101 B
#740000
0"
#745000
1!
#747000
b1000 8
b110100010000001111111111111011 ;
b100 <
b1110 J
b1110 E
b1100111001110111100000000000 D
#750000
0!
#755000
1"
#757000
b110100010000001111111111111011 G
b100 I
b0 C
b1100111001110111100000000000 A
b111100000000000 @
b111 ?
b111 >
b1110 B
#760000
0"
#765000
1!
#767000
b1001 J
b1001 E
1K
b10100010000110001100000000000 D
b111 8
b1100111001110111100000000000 ;
b0 <
#770000
0!
#775000
1"
#777000
b10100010000110001100000000000 A
b1100000000000 @
b1011010000 ?
b1 >
b1001 B
b1100111001110111100000000000 G
b0 I
#780000
0"
#785000
1!
#787000
b1011010000 8
0K
b10100010000110001100000000000 ;
b1010 J
b1010 E
b101100010000100000000000000001 D
#790000
0!
#795000
1"
#797000
b1011010000 F
b10100010000110001100000000000 G
b1 C
b101100010000100000000000000001 A
b1 @
b1 ?
b1010 B
#800000
0"
#805000
1!
#807000
b1011 J
b1011 E
b1100111001110111100000000000 D
b0 8
b101100010000100000000000000001 ;
b1 <
#810000
0!
#815000
1"
#817000
b0 C
b1100111001110111100000000000 A
b111100000000000 @
b111 ?
b111 >
b1011 B
b0 F
b101100010000100000000000000001 G
b1 I
#820000
0"
#825000
1!
#827000
b111 8
b1100111001110111100000000000 ;
b0 <
b1100 J
b1100 E
#830000
0!
#835000
1"
#837000
b111 F
b1100111001110111100000000000 G
b0 I
b1100 B
#840000
0"
#845000
1!
#847000
b1101 J
b1101 E
b110100010000001111111111111011 D
#850000
0!
#855000
1"
#857000
b100 C
b110100010000001111111111111011 A
b11111111111111111111111111111011 @
b0 ?
b0 >
b1101 B
#860000
0"
#865000
1!
#867000
1:
b1000 8
b110100010000001111111111111011 ;
b100 <
b1110 J
b1110 E
b1100111001110111100000000000 D
#870000
0!
#875000
1"
#877000
b110100010000001111111111111011 G
b100 I
b0 C
b1100111001110111100000000000 A
b111100000000000 @
b111 ?
b111 >
b1110 B
#880000
0"
#885000
1!
#887000
b1111 J
b1111 E
b111 8
b1100111001110111100000000000 ;
b0 <
#890000
0!
#895000
1"
#897000
b1111 B
b1100111001110111100000000000 G
b0 I
#900000
0"
#905000
1!
#907000
b10000 J
b10000 E
b100100001000111111111111111110 D
#910000
0!
#915000
1"
#917000
b11 C
b100100001000111111111111111110 A
b11111111111111111111111111111110 @
b1011010000 ?
b11001000 >
b10000 B
#920000
0"
#925000
1!
#927000
b10001 J
b10001 E
b11111100000000000000000000000000 D
b1011010000 9
b11000110 8
b100100001000111111111111111110 ;
b11 <
#930000
0!
#935000
1"
#937000
b101 C
b11111100000000000000000000000000 A
b0 @
b0 ?
b0 >
b10001 B
b100100001000111111111111111110 G
b11 I
#940000
0"
#945000
1!
#947000
b11111100000000000000000000000000 ;
b101 <
b10010 J
b10010 E
bx D
#950000
0!
#955000
1"
#957000
b11111100000000000000000000000000 G
b101 I
bx A
bx @
bx ?
bx >
b10010 B
#960000
0"
#965000
1!
#967000
b10011 J
b10011 E
bx ;
1=
